mapox/__init__.py
mapox/client.py
mapox/config.py
mapox/environment.py
mapox/map_generator.py
mapox/renderer.py
mapox/specs.py
mapox/timestep.py
mapox/envs/__init__.py
mapox/envs/constance.py
mapox/envs/grid_return.py
mapox/envs/king_hill.py
mapox/envs/scouts.py
mapox/envs/traveling_salesman.py
mapox/utils/__init__.py
mapox/utils/encode_one_hot.py
mapox/utils/video_writter.py
mapox/wrappers/__init__.py
mapox/wrappers/multitask.py
mapox/wrappers/task_id_wrapper.py
mapox/wrappers/vector.py
mapox-0.1.0.dist-info/METADATA
mapox-0.1.0.dist-info/WHEEL
mapox-0.1.0.dist-info/RECORD
